{
  "date": "2026-07-13",
  "results": [
    {
      "symbol": "CHOG",
      "invite": "chog",
      "memberCount": 43177,
      "onlineCount": 1443,
      "guildName": "Chog"
    },
    {
      "symbol": "BONK",
      "invite": "qaQa6M6mN2",
      "memberCount": 33162,
      "onlineCount": 1843,
      "guildName": "Bonk"
    },
    {
      "symbol": "PENGU",
      "invite": "pudgypenguins",
      "memberCount": 162354,
      "onlineCount": 8878,
      "guildName": "Pudgy Penguins"
    },
    {
      "symbol": "SOL",
      "invite": "solana",
      "memberCount": 148760,
      "onlineCount": 6110,
      "guildName": "Solana Tech"
    },
    {
      "symbol": "SUI",
      "invite": "sui",
      "memberCount": 896646,
      "onlineCount": 12579,
      "guildName": "Sui"
    },
    {
      "symbol": "MON",
      "invite": "monad",
      "memberCount": 635502,
      "onlineCount": 12403,
      "guildName": "Monad"
    },
    {
      "symbol": "HYPE",
      "invite": "hyperliquid",
      "memberCount": 87867,
      "onlineCount": 10232,
      "guildName": "Hyperliquid"
    },
    {
      "symbol": "TAO",
      "invite": "5MGtAz5kW",
      "memberCount": 49792,
      "onlineCount": 4739,
      "guildName": "Bittensor"
    }
  ]
}