{
  "symbol": "ANSEM",
  "coingeckoId": "the-black-bull",
  "series": [
    {
      "date": "2026-06-21",
      "price": 0.0005231233277821076
    },
    {
      "date": "2026-06-22",
      "price": 0.0005114260377111597
    },
    {
      "date": "2026-06-23",
      "price": 0.00045717762150520024
    },
    {
      "date": "2026-06-24",
      "price": 0.00021469661592494205
    },
    {
      "date": "2026-06-25",
      "price": 0.0001950999897689895
    },
    {
      "date": "2026-06-26",
      "price": 0.0002456346613731749
    },
    {
      "date": "2026-06-27",
      "price": 0.008767726997765823
    },
    {
      "date": "2026-06-28",
      "price": 0.08905866141830854
    },
    {
      "date": "2026-06-29",
      "price": 0.12438971287029885
    },
    {
      "date": "2026-06-30",
      "price": 0.13643073515929446
    },
    {
      "date": "2026-07-01",
      "price": 0.15508399981611723
    },
    {
      "date": "2026-07-02",
      "price": 0.17154880089775368
    },
    {
      "date": "2026-07-03",
      "price": 0.32741818988388477
    },
    {
      "date": "2026-07-04",
      "price": 0.3318096701257582
    },
    {
      "date": "2026-07-05",
      "price": 0.3298102928045272
    }
  ]
}