{
  "date": "2026-07-14",
  "results": [
    {
      "symbol": "CHOG",
      "date": "2026-07-14",
      "mentionCount": 796,
      "collectedAt": "2026-07-15T08:39:00.327Z"
    },
    {
      "symbol": "PEPE",
      "date": "2026-07-14",
      "mentionCount": 19320,
      "collectedAt": "2026-07-15T08:39:00.327Z"
    },
    {
      "symbol": "WIF",
      "date": "2026-07-14",
      "mentionCount": 1930,
      "collectedAt": "2026-07-15T08:39:00.327Z"
    },
    {
      "symbol": "BONK",
      "date": "2026-07-14",
      "mentionCount": 4387,
      "collectedAt": "2026-07-15T08:39:00.327Z"
    },
    {
      "symbol": "BRETT",
      "date": "2026-07-14",
      "mentionCount": 13717,
      "collectedAt": "2026-07-15T08:39:00.327Z"
    },
    {
      "symbol": "PENGU",
      "date": "2026-07-14",
      "mentionCount": 5768,
      "collectedAt": "2026-07-15T08:39:00.327Z"
    },
    {
      "symbol": "FARTCOIN",
      "date": "2026-07-14",
      "mentionCount": 1869,
      "collectedAt": "2026-07-15T08:39:00.327Z"
    },
    {
      "symbol": "ANSEM",
      "date": "2026-07-14",
      "mentionCount": 53410,
      "collectedAt": "2026-07-15T08:39:00.327Z"
    },
    {
      "symbol": "CASHCAT",
      "date": "2026-07-14",
      "mentionCount": 10382,
      "collectedAt": "2026-07-15T08:39:00.327Z"
    },
    {
      "symbol": "BTC",
      "date": "2026-07-14",
      "mentionCount": 105533,
      "collectedAt": "2026-07-15T08:39:00.327Z"
    },
    {
      "symbol": "ETH",
      "date": "2026-07-14",
      "mentionCount": 46930,
      "collectedAt": "2026-07-15T08:39:00.327Z"
    },
    {
      "symbol": "SOL",
      "date": "2026-07-14",
      "mentionCount": 206513,
      "collectedAt": "2026-07-15T08:39:00.327Z"
    },
    {
      "symbol": "XRP",
      "date": "2026-07-14",
      "mentionCount": 22028,
      "collectedAt": "2026-07-15T08:39:00.327Z"
    },
    {
      "symbol": "SUI",
      "date": "2026-07-14",
      "mentionCount": 11000,
      "collectedAt": "2026-07-15T08:39:00.327Z"
    },
    {
      "symbol": "MON",
      "date": "2026-07-14",
      "mentionCount": 84154,
      "collectedAt": "2026-07-15T08:39:00.327Z"
    },
    {
      "symbol": "HYPE",
      "date": "2026-07-14",
      "mentionCount": 48386,
      "collectedAt": "2026-07-15T08:39:00.327Z"
    },
    {
      "symbol": "TAO",
      "date": "2026-07-14",
      "mentionCount": 21450,
      "collectedAt": "2026-07-15T08:39:00.327Z"
    },
    {
      "symbol": "AKT",
      "date": "2026-07-14",
      "mentionCount": 1442,
      "collectedAt": "2026-07-15T08:39:00.327Z"
    },
    {
      "symbol": "STRK",
      "date": "2026-07-14",
      "mentionCount": 729,
      "collectedAt": "2026-07-15T08:39:00.327Z"
    }
  ]
}